{
  "tasks": [
    {
      "id": "273bec95-b6b5-492f-983b-b91cb1cc1bcf",
      "title": "Task 01",
      "description": "Descrição da Task 01",
      "completed_at": null,
      "created_at": "2023-05-04T02:48:25.171Z",
      "updated_at": "2023-05-04T02:48:25.171Z"
    },
    {
      "id": "e4b7625c-67c4-4bfa-a97d-c7c4b55dba15",
      "title": "Task 02",
      "description": "Descrição da Task 02",
      "completed_at": null,
      "created_at": "2023-05-04T02:48:25.185Z",
      "updated_at": "2023-05-04T02:48:25.185Z"
    },
    {
      "id": "d1f44665-cea7-4b7e-acf5-aafa620ad9f8",
      "title": "Task 03",
      "description": "Descrição da Task 03",
      "completed_at": null,
      "created_at": "2023-05-04T02:48:25.189Z",
      "updated_at": "2023-05-04T02:48:25.189Z"
    },
    {
      "id": "270c5c0c-9146-4c3e-b9e7-9bc4c1d1bd99",
      "title": "Task 04",
      "description": "Descrição da Task 04",
      "completed_at": null,
      "created_at": "2023-05-04T02:48:25.195Z",
      "updated_at": "2023-05-04T02:48:25.195Z"
    },
    {
      "id": "d5bd9c5d-33dc-47c6-ac61-3f37a538a560",
      "title": "Task 05",
      "description": "Descrição da Task 05",
      "completed_at": null,
      "created_at": "2023-05-04T02:48:25.199Z",
      "updated_at": "2023-05-04T02:48:25.199Z"
    },
    {
      "id": "494dfad9-2ecc-40e8-9296-75544f3e0378",
      "title": "Task 06",
      "description": "Descrição da Task 06",
      "completed_at": null,
      "created_at": "2023-05-04T02:48:25.202Z",
      "updated_at": "2023-05-04T02:48:25.202Z"
    }
  ]
}